stacks_embed/__init__.py
stacks_embed/admin.py
stacks_embed/apps.py
stacks_embed/models.py
stacks_embed/registry.py
stacks_embed/serializers.py
stacks_embed/stuff.py
stacks_embed/utils.py
stacks_embed/migrations/0001_initial.py
stacks_embed/migrations/0002_auto_20150528_1451.py
stacks_embed/migrations/0003_auto_20150528_1453.py
stacks_embed/migrations/0004_remove_stacksembedlist_list_name.py
stacks_embed/migrations/0005_auto_20150529_2033.py
stacks_embed/migrations/0006_stacksembed_overline.py
stacks_embed/migrations/__init__.py
stacks_embed/pbs_cove/__init__.py
stacks_embed/pbs_cove/stacks_embed_service.py
stacks_embed/soundcloud/__init__.py
stacks_embed/soundcloud/stacks_embed_service.py
stacks_embed/static/js/stacks_embed.js
stacks_embed/static/sass/_stacks_embed.scss
stacks_embed/templates/stacks_embed/stacksembed/stacksembed-embed_left_content_right.html
stacks_embed/templates/stacks_embed/stacksembed/stacksembed-embed_right_content_left.html
stacks_embed/templates/stacks_embed/stacksembed/stacksembed-full_width.html
stacks_embed/templates/stacks_embed/stacksembedlist/stacksembedlist-1up.html
stacks_embed/templates/stacks_embed/stacksembedlist/stacksembedlist-2up.html
stacks_embed/templates/stacks_embed/stacksembedlist/stacksembedlist-3up.html
stacks_embed/templates/stacks_embed/stacksembedlist/stacksembedlist-gallery.html
stacks_embed/vimeo/__init__.py
stacks_embed/vimeo/stacks_embed_service.py
stacks_embed/youtube/__init__.py
stacks_embed/youtube/stacks_embed_service.py
stacks_embed-0.2.2.dist-info/DESCRIPTION.rst
stacks_embed-0.2.2.dist-info/LICENSE.txt
stacks_embed-0.2.2.dist-info/METADATA
stacks_embed-0.2.2.dist-info/RECORD
stacks_embed-0.2.2.dist-info/WHEEL
stacks_embed-0.2.2.dist-info/metadata.json
stacks_embed-0.2.2.dist-info/top_level.txt
