Metadata-Version: 2.0
Name: stacks-embed
Version: 0.2.2
Summary: A Stacks application for handling embeddable media.
Home-page: http://stacks.wgbhdigital.org/
Author: Jonathan Ellenberger
Author-email: jonathan_ellenberger@wgbh.org
License: MIT License, see LICENSE
Platform: UNKNOWN
Classifier: Framework :: Django
Classifier: Framework :: Django :: 1.7
Classifier: Framework :: Django :: 1.8
Classifier: License :: OSI Approved :: MIT License
Classifier: Natural Language :: English
Classifier: Programming Language :: Python
Classifier: Programming Language :: Python :: 2
Classifier: Programming Language :: Python :: 2.7
Classifier: Development Status :: 3 - Alpha
Requires-Dist: django-textplusstuff (>=0.4)
Requires-Dist: django-versatileimagefield (>=1.0.2)
Requires-Dist: stacks-page (>=0.1.1)
